safehttpx/__init__.py
safehttpx-0.1.5.dist-info/METADATA
safehttpx-0.1.5.dist-info/WHEEL
safehttpx-0.1.5.dist-info/licenses/LICENSE
safehttpx-0.1.5.dist-info/RECORD
