Metadata-Version: 2.3
Name: safehttpx
Version: 0.1.5
Summary: A small Python library created to help developers protect their applications from Server Side Request Forgery (SSRF) attacks.
Project-URL: homepage, https://github.com/gradio-app/safehttpx
Project-URL: repository, https://github.com/gradio-app/safehttpx
Author-email: Abubakar Abid <abubakar@hf.co>
Classifier: License :: OSI Approved :: MIT License
Classifier: Operating System :: OS Independent
Classifier: Programming Language :: Python :: 3
Requires-Python: >3.9
Requires-Dist: httpx
Provides-Extra: dev
Requires-Dist: pytest; extra == 'dev'
